heedy/__init__.py
heedy/apps.py
heedy/base.py
heedy/datasets.py
heedy/kv.py
heedy/notifications.py
heedy/plugins.py
heedy/users.py
heedy/objects/__init__.py
heedy/objects/dashboard.py
heedy/objects/objects.py
heedy/objects/registry.py
heedy/objects/timeseries.py
tests/__init__.py
tests/test_basic.py
tests/test_bugfixes.py
tests/test_dashboard.py
tests/test_datasets.py
tests/test_docs.py
tests/test_plugin.py
tests/test_timeseries.py
heedy-0.2.0.dist-info/METADATA
heedy-0.2.0.dist-info/WHEEL
heedy-0.2.0.dist-info/top_level.txt
heedy-0.2.0.dist-info/RECORD
