Metadata-Version: 2.1
Name: heedy
Version: 0.2.0
Summary: A Python library for interfacing with Heedy
Home-page: https://github.com/heedy/heedy
Author: Heedy Contributors
License: apache2
Platform: UNKNOWN
Classifier: Intended Audience :: Developers
Classifier: Intended Audience :: Science/Research
Classifier: Programming Language :: Python :: 3
Classifier: Programming Language :: Python :: 3.7
Requires-Python: >=3.7.0
Requires-Dist: aiohttp
Requires-Dist: dateparser
Requires-Dist: requests
Provides-Extra: dataframes
Requires-Dist: pandas ; extra == 'dataframes'
